Anisearch/__init__.py
Anisearch/connection.py
Anisearch/datatype.py
Anisearch/get.py
Anisearch/search.py
Anisearch-1.1.0.dist-info/LICENSE
Anisearch-1.1.0.dist-info/METADATA
Anisearch-1.1.0.dist-info/WHEEL
Anisearch-1.1.0.dist-info/top_level.txt
Anisearch-1.1.0.dist-info/RECORD
