Metadata-Version: 2.1
Name: Anisearch
Version: 1.1.0
Summary: Anisearch is the lib for accessing anime or manga from anilist.co on the Python Platform.
Home-page: https://github.com/MeGaNeKoS/Anisearch
Author: めがねこ
Author-email: evictory91@gmail.com
License: MIT
Keywords: Anime Manga Anilist
Classifier: Development Status :: 5 - Production/Stable
Classifier: Intended Audience :: Developers
Classifier: License :: OSI Approved :: MIT License
Classifier: Programming Language :: Python :: 3
License-File: LICENSE
Requires-Dist: requests
